pydantic_db_backend_common/__init__.py
pydantic_db_backend_common/exceptions/__init__.py
pydantic_db_backend_common/indexes/__init__.py
pydantic_db_backend_common/pagination/__init__.py
pydantic_db_backend_common/pydantic/__init__.py
pydantic_db_backend_common/utils/__init__.py
pydantic_db_backend_common-2.3.1.dist-info/METADATA
pydantic_db_backend_common-2.3.1.dist-info/WHEEL
pydantic_db_backend_common-2.3.1.dist-info/RECORD
