Metadata-Version: 2.1
Name: pydantic-db-backend-common
Version: 2.3.1
Summary: 
Author: mba
Author-email: bartel@electronic-shop.lu
Requires-Python: >=3.11,<4.0
Classifier: Programming Language :: Python :: 3
Classifier: Programming Language :: Python :: 3.11
Requires-Dist: iso8601 (>=2.1.0,<3.0.0)
Requires-Dist: pydantic (>=2.4.2,<3.0.0)
Requires-Dist: webexception (>=1.0.4,<2.0.0)
